gym_stopping/__init__.py
gym_stopping/envs/__init__.py
gym_stopping/envs/stopping_env.py
gym_stopping-0.0.2.dist-info/LICENSE
gym_stopping-0.0.2.dist-info/METADATA
gym_stopping-0.0.2.dist-info/WHEEL
gym_stopping-0.0.2.dist-info/top_level.txt
gym_stopping-0.0.2.dist-info/RECORD
