Metadata-Version: 2.1
Name: gym-stopping
Version: 0.0.2
Summary: A OpenAI Gym Env for continuous control
Author: Claudia Viaro
License: MIT
Platform: UNKNOWN
License-File: LICENSE
Requires-Dist: gym
